oom/__init__.py
oom/__main__.py
oom/exit_on_out_of_ram.py
tests/__init__.py
oom-0.1.0.dist-info/LICENSE
oom-0.1.0.dist-info/METADATA
oom-0.1.0.dist-info/WHEEL
oom-0.1.0.dist-info/top_level.txt
oom-0.1.0.dist-info/RECORD
