Metadata-Version: 2.1
Name: oom
Version: 0.1.0
Summary: Prevents freezing of your machine when it's running out of RAM
Home-page: https://gitlab.com/aduard.kononov/oom
Author: Eduard Konanau
Author-email: aduard.kononov@gmail.com
License: UNKNOWN
Platform: UNKNOWN
Classifier: Programming Language :: Python :: 3
Classifier: License :: OSI Approved :: MIT License
Classifier: Operating System :: OS Independent
Requires-Python: >=3.6
